{
  "includeWebResults": false,
  "language": "id",
  "locationQuery": "Jawa Barat, Indonesia",
  "maxCrawledPlacesPerSearch": 5,
  "maximumLeadsEnrichmentRecords": 0,
  "scrapeContacts": false,
  "scrapeDirectories": false,
  "scrapeImageAuthors": false,
  "scrapeOrderOnline": false,
  "scrapePlaceDetailPage": true,
  "scrapeReviewsPersonalData": false,
  "scrapeSocialMediaProfiles": {
    "facebooks": false,
    "instagrams": false,
    "tiktoks": false,
    "twitters": false,
    "youtubes": false
  },
  "scrapeTableReservationProvider": false,
  "searchStringsArray": [
    "villa arjuna 60 Padalarang Kabupaten Bandung Barat Jawa Barat Indonesia",
    "villa kota Bunga little indian Padalarang Kabupaten Bandung Barat Jawa Barat Indonesia",
    "Alayam villa Padalarang Kabupaten Bandung Barat Jawa Barat Indonesia",
    "Shida Village Lembang Kabupaten Bandung Barat Jawa Barat Indonesia",
    "Villa Ravani Bandung Bandung Jawa Barat Indonesia",
    "villa Camsal Boock H 10 No3 Padalarang Kabupaten Bandung Barat Jawa Barat Indonesia",
    "Villa Argapuri Resort K.10 Ciwidey Kabupaten Bandung Jawa Barat Indonesia",
    "Villa rian Ciwidey Kabupaten Bandung Jawa Barat Indonesia",
    "Camping hutan pinus rahong - Tent Pangalengan Kabupaten Bandung Jawa Barat Indonesia",
    "Camping hutan pinus singkur rahong - Tent Pangalengan Kabupaten Bandung Jawa Barat Indonesia",
    "Kawoeng kabin - Tent Bandung Jawa Barat Indonesia",
    "Mala Green Camp - Tent Pangalengan Kabupaten Bandung Jawa Barat Indonesia",
    "SHAKILLA HOUSE 4 PESONA SYARIAH CIANJUR Padalarang Kabupaten Bandung Barat Jawa Barat Indonesia",
    "Wulandari Camping ground Riverside - Tent Pangalengan Kabupaten Bandung Jawa Barat Indonesia",
    "ALI1 Pondok Orange 1 Ciwidey Ciwidey Kabupaten Bandung Jawa Barat Indonesia",
    "ALIFA SHAKILLA HOUSE 3 SYARIAH LIMBANGAN CIANJUR Padalarang Kabupaten Bandung Barat Jawa Barat Indonesia",
    "ALLIKA SHAKILLA HOUSE 3 SYARIAH LIMBANGAN CIANJUR Padalarang Kabupaten Bandung Barat Jawa Barat Indonesia",
    "Ace Inn at KBP near IKEA Wahoo Yogya Junction KBP Padalarang Kabupaten Bandung Barat Jawa Barat Indonesia",
    "Aira Glamping Bandung Jawa Barat Indonesia",
    "Alifa Shakilla House 3 Syariah Limbangansari Padalarang Kabupaten Bandung Barat Jawa Barat Indonesia",
    "Alkasturi syariah Cottage Ciwidey Bandung Ciwidey Kabupaten Bandung Jawa Barat Indonesia",
    "Allika Shakilla House 3 Limbangansari Syariah Padalarang Kabupaten Bandung Barat Jawa Barat Indonesia",
    "Amazing Comfy House in Bandung Padalarang Kabupaten Bandung Barat Jawa Barat Indonesia",
    "Aqilla Shakilla House 3 Syariah Limbanagnsari Padalarang Kabupaten Bandung Barat Jawa Barat Indonesia",
    "Argapuri Resort Ciwidey Kabupaten Bandung Jawa Barat Indonesia",
    "Arjuna Ciwidey Kabupaten Bandung Jawa Barat Indonesia",
    "Arjuna cottage rafting - Tent Pangalengan Kabupaten Bandung Jawa Barat Indonesia",
    "Azalea 1 - Private Glamping Bandung Jawa Barat Indonesia",
    "Bima Ciwidey Kabupaten Bandung Jawa Barat Indonesia",
    "Bisma Ciwidey Kabupaten Bandung Jawa Barat Indonesia",
    "Bumi Castle Luxury Living di Kota Baru Parahyangan Padalarang Kabupaten Bandung Barat Jawa Barat Indonesia",
    "Cabin 97 Ciwidey Kabupaten Bandung Jawa Barat Indonesia",
    "Camping Pines singkur reverside - Tent Pangalengan Kabupaten Bandung Jawa Barat Indonesia",
    "Cibodas Get Away in West Java Padalarang Kabupaten Bandung Barat Jawa Barat Indonesia",
    "Cozy tropical houses with humble neighbourhood Padalarang Kabupaten Bandung Barat Jawa Barat Indonesia",
    "D'Gloria Glamping Bandung Jawa Barat Indonesia",
    "Davion House near IKEA KBP by YourHome Padalarang Kabupaten Bandung Barat Jawa Barat Indonesia",
    "Dayang Arum Glamping Bandung Jawa Barat Indonesia",
    "Dayang Rengganis Dome 2 Bandung Jawa Barat Indonesia",
    "Family Cabin with Lake/Mountain View in Ciwidey Ciwidey Kabupaten Bandung Jawa Barat Indonesia",
    "Family Staycation, Near Lembang With Complete Facilities Lembang Kabupaten Bandung Barat Jawa Barat Indonesia",
    "Glamping [Sunrise] - 2 : Argapuri Jungle Resort Ciwidey Kabupaten Bandung Jawa Barat Indonesia",
    "Glamping triangle riyadhi 2 Bandung Jawa Barat Indonesia",
    "Good places, service, good view. Perfect choices. Ciwidey Kabupaten Bandung Jawa Barat Indonesia",
    "Hanara Private Glamping Bandung Jawa Barat Indonesia",
    "Keyla Private Dome Bandung Jawa Barat Indonesia",
    "Khaira Shakilla House 3 Syariah Limbangansari Padalarang Kabupaten Bandung Barat Jawa Barat Indonesia",
    "Kota Bunga A Padalarang Kabupaten Bandung Barat Jawa Barat Indonesia"
  ],
  "skipClosedPlaces": false,
  "verifyLeadsEnrichmentEmails": false
}